creatio_api_py/__init__.py
creatio_api_py/api.py
creatio_api_py/encryption.py
creatio_api_py/logs.py
creatio_api_py/py.typed
creatio_api_py/utils.py
creatio_api_py-1.3.3.dist-info/LICENSE
creatio_api_py-1.3.3.dist-info/METADATA
creatio_api_py-1.3.3.dist-info/WHEEL
creatio_api_py-1.3.3.dist-info/RECORD
