Metadata-Version: 2.3
Name: creatio-api-py
Version: 1.3.3
Summary: Python client for Creatio OData API
License: GPL-3.0-only
Author: Alejandro González Momblán
Author-email: alejandro.gonzalez.momblan@evoluciona.es
Requires-Python: >3.9.1,<4.0
Classifier: License :: OSI Approved :: GNU General Public License v3 (GPLv3)
Classifier: Programming Language :: Python :: 3
Classifier: Programming Language :: Python :: 3.10
Classifier: Programming Language :: Python :: 3.11
Classifier: Programming Language :: Python :: 3.12
Classifier: Programming Language :: Python :: 3.13
Requires-Dist: cryptography (>=44.0.0,<45.0.0)
Requires-Dist: pydantic (>=2.8.2,<3.0.0)
Requires-Dist: python-dotenv (>=1.0.1,<2.0.0)
Requires-Dist: requests (>=2.31.0,<3.0.0)
Requires-Dist: requests-cache (>=1.1.1,<2.0.0)
Requires-Dist: requests-pprint (>=1.0.0,<2.0.0)
Requires-Dist: rich (>=13.7.0,<14.0.0)
Project-URL: Repository, https://github.com/yisuschrist/creatio-api-py
